{
  "allowedFileTypes": "[\".csv\", \".json\"]",
  "animateLoading": true,
  "borderRadius": "{{appsmith.theme.borderRadius.appBorderRadius}}",
  "bottomRow": 78,
  "boxShadow": "none",
  "buttonColor": "{{appsmith.theme.colors.primaryColor}}",
  "dynamicBindingPathList": [
    {
      "key": "buttonColor"
    },
    {
      "key": "borderRadius"
    }
  ],
  "dynamicPropertyPathList": [
    {
      "key": "allowedFileTypes"
    }
  ],
  "dynamicTriggerPathList": [
    {
      "key": "onFilesSelected"
    }
  ],
  "dynamicTyping": true,
  "fileDataType": "Base64",
  "files": [],
  "isDefaultClickDisabled": true,
  "isDisabled": false,
  "isLoading": false,
  "isRequired": false,
  "isVisible": true,
  "key": "83fccdo0pf",
  "label": "Upload JSON/CSV",
  "leftColumn": 2,
  "maxFileSize": 5,
  "maxNumFiles": 1,
  "minWidth": 120,
  "mobileBottomRow": 78,
  "mobileLeftColumn": 2,
  "mobileRightColumn": 18,
  "mobileTopRow": 74,
  "needsErrorInfo": false,
  "onFilesSelected": "{{readFile.upload();}}",
  "parentColumnSpace": 9.5400390625,
  "parentId": "ohhkg7lwl7",
  "parentRowSpace": 10,
  "renderMode": "CANVAS",
  "responsiveBehavior": "hug",
  "rightColumn": 18,
  "selectedFiles": [],
  "topRow": 74,
  "type": "FILE_PICKER_WIDGET_V2",
  "version": 1,
  "widgetId": "7vd0zwwkk4",
  "widgetName": "FilePicker1"
}